[{"pl":"pub const Status = extern enum","src":7,"more_decls":{"doc_comment":"The operation completed successfully.","pl":"Success = 0","src":9,"more_decls":null}{"doc_comment":"The image failed to load.","pl":"LoadError = high_bit | 1","src":12,"more_decls":null}{"doc_comment":"A parameter was incorrect.","pl":"InvalidParameter = high_bit | 2","src":15,"more_decls":null}{"doc_comment":"The operation is not supported.","pl":"Unsupported = high_bit | 3","src":18,"more_decls":null}{"doc_comment":"The buffer was not the proper size for the request.","pl":"BadBufferSize = high_bit | 4","src":21,"more_decls":null}{"doc_comment":"The buffer is not large enough to hold the requested data. The required buffer size is returned in the appropriate parameter when this error occurs.","pl":"BufferTooSmall = high_bit | 5","src":24,"more_decls":null}{"doc_comment":"There is no data pending upon return.","pl":"NotReady = high_bit | 6","src":27,"more_decls":null}{"doc_comment":"The physical device reported an error while attempting the operation.","pl":"DeviceError = high_bit | 7","src":30,"more_decls":null}{"doc_comment":"The device cannot be written to.","pl":"WriteProtected = high_bit | 8","src":33,"more_decls":null}{"doc_comment":"A resource has run out.","pl":"OutOfResources = high_bit | 9","src":36,"more_decls":null}{"doc_comment":"An inconstancy was detected on the file system causing the operating to fail.","pl":"VolumeCorrupted = high_bit | 10","src":39,"more_decls":null}{"doc_comment":"There is no more space on the file system.","pl":"VolumeFull = high_bit | 11","src":42,"more_decls":null}{"doc_comment":"The device does not contain any medium to perform the operation.","pl":"NoMedia = high_bit | 12","src":45,"more_decls":null}{"doc_comment":"The medium in the device has changed since the last access.","pl":"MediaChanged = high_bit | 13","src":48,"more_decls":null}{"doc_comment":"The item was not found.","pl":"NotFound = high_bit | 14","src":51,"more_decls":null}{"doc_comment":"Access was denied.","pl":"AccessDenied = high_bit | 15","src":54,"more_decls":null}{"doc_comment":"The server was not found or did not respond to the request.","pl":"NoResponse = high_bit | 16","src":57,"more_decls":null}{"doc_comment":"A mapping to a device does not exist.","pl":"NoMapping = high_bit | 17","src":60,"more_decls":null}{"doc_comment":"The timeout time expired.","pl":"Timeout = high_bit | 18","src":63,"more_decls":null}{"doc_comment":"The protocol has not been started.","pl":"NotStarted = high_bit | 19","src":66,"more_decls":null}{"doc_comment":"The protocol has already been started.","pl":"AlreadyStarted = high_bit | 20","src":69,"more_decls":null}{"doc_comment":"The operation was aborted.","pl":"Aborted = high_bit | 21","src":72,"more_decls":null}{"doc_comment":"An ICMP error occurred during the network operation.","pl":"IcmpError = high_bit | 22","src":75,"more_decls":null}{"doc_comment":"A TFTP error occurred during the network operation.","pl":"TftpError = high_bit | 23","src":78,"more_decls":null}{"doc_comment":"A protocol error occurred during the network operation.","pl":"ProtocolError = high_bit | 24","src":81,"more_decls":null}{"doc_comment":"The function encountered an internal version that was incompatible with a version requested by the caller.","pl":"IncompatibleVersion = high_bit | 25","src":84,"more_decls":null}{"doc_comment":"The function was not performed due to a security violation.","pl":"SecurityViolation = high_bit | 26","src":87,"more_decls":null}{"doc_comment":"A CRC error was detected.","pl":"CrcError = high_bit | 27","src":90,"more_decls":null}{"doc_comment":"Beginning or end of media was reached","pl":"EndOfMedia = high_bit | 28","src":93,"more_decls":null}{"doc_comment":"The end of the file was reached.","pl":"EndOfFile = high_bit | 31","src":96,"more_decls":null}{"doc_comment":"The language specified was invalid.","pl":"InvalidLanguage = high_bit | 32","src":99,"more_decls":null}{"doc_comment":"The security status of the data is unknown or compromised and the data must be updated or replaced to restore a valid security status.","pl":"CompromisedData = high_bit | 33","src":102,"more_decls":null}{"doc_comment":"There is an address conflict address allocation","pl":"IpAddressConflict = high_bit | 34","src":105,"more_decls":null}{"doc_comment":"A HTTP error occurred during the network operation.","pl":"HttpError = high_bit | 35","src":108,"more_decls":null}{"pl":"NetworkUnreachable = high_bit | 100","src":110,"more_decls":null}{"pl":"HostUnreachable = high_bit | 101","src":112,"more_decls":null}{"pl":"ProtocolUnreachable = high_bit | 102","src":114,"more_decls":null}{"pl":"PortUnreachable = high_bit | 103","src":116,"more_decls":null}{"pl":"ConnectionFin = high_bit | 104","src":118,"more_decls":null}{"pl":"ConnectionReset = high_bit | 105","src":120,"more_decls":null}{"pl":"ConnectionRefused = high_bit | 106","src":122,"more_decls":null}{"doc_comment":"The string contained one or more characters that the device could not render and were skipped.","pl":"WarnUnknownGlyph = 1","src":125,"more_decls":null}{"doc_comment":"The handle was closed, but the file was not deleted.","pl":"WarnDeleteFailure = 2","src":128,"more_decls":null}{"doc_comment":"The handle was closed, but the data to the file was not flushed properly.","pl":"WarnWriteFailure = 3","src":131,"more_decls":null}{"doc_comment":"The resulting buffer was too small, and the data was truncated to the buffer size.","pl":"WarnBufferTooSmall = 4","src":134,"more_decls":null}{"doc_comment":"The data has not been updated within the timeframe set by localpolicy for this type of data.","pl":"WarnStaleData = 5","src":137,"more_decls":null}{"doc_comment":"The resulting buffer contains UEFI-compliant file system.","pl":"WarnFileSystem = 6","src":140,"more_decls":null}{"doc_comment":"The operation will be processed across a system reset.","pl":"WarnResetRequired = 7","src":143,"more_decls":null}{"pl":"_","src":145,"more_decls":null}}]