[{"doc_comment":"This matches the libc clone function.","pl":"extern fn clone(func: fn (arg: usize) callconv(.C) u8, stack: usize, flags: u32, arg: usize, ptid: *i32, tls: usize, ctid: *i32) usize","src":186,"more_decls":null}{"pl":"fn syscall0(number: SYS) usize","src":7,"more_decls":null}{"pl":"fn syscall_pipe(fd: *[2]i32) usize","src":19,"more_decls":null}{"pl":"fn syscall1(number: SYS, arg1: usize) usize","src":38,"more_decls":null}{"pl":"fn syscall2(number: SYS, arg1: usize, arg2: usize) usize","src":51,"more_decls":null}{"pl":"fn syscall3(number: SYS, arg1: usize, arg2: usize, arg3: usize) usize","src":65,"more_decls":null}{"pl":"fn syscall4(number: SYS, arg1: usize, arg2: usize, arg3: usize, arg4: usize) usize","src":80,"more_decls":null}{"pl":"fn syscall5(number: SYS, arg1: usize, arg2: usize, arg3: usize, arg4: usize, arg5: usize) usize","src":96,"more_decls":null}{"pl":"fn syscall6(\n    number: SYS,\n    arg1: usize,\n    arg2: usize,\n    arg3: usize,\n    arg4: usize,\n    arg5: usize,\n    arg6: usize,\n) usize","src":120,"more_decls":null}{"pl":"fn syscall7(\n    number: SYS,\n    arg1: usize,\n    arg2: usize,\n    arg3: usize,\n    arg4: usize,\n    arg5: usize,\n    arg6: usize,\n    arg7: usize,\n) usize","src":151,"more_decls":null}{"pl":"fn restore() callconv(.Naked) void","src":188,"more_decls":null}{"pl":"fn restore_rt() callconv(.Naked) void","src":196,"more_decls":null}]