[{"pl":"const TAG_padding = 0x00","src":5,"more_decls":null}{"pl":"const TAG_array_type = 0x01","src":6,"more_decls":null}{"pl":"const TAG_class_type = 0x02","src":7,"more_decls":null}{"pl":"const TAG_entry_point = 0x03","src":8,"more_decls":null}{"pl":"const TAG_enumeration_type = 0x04","src":9,"more_decls":null}{"pl":"const TAG_formal_parameter = 0x05","src":10,"more_decls":null}{"pl":"const TAG_imported_declaration = 0x08","src":11,"more_decls":null}{"pl":"const TAG_label = 0x0a","src":12,"more_decls":null}{"pl":"const TAG_lexical_block = 0x0b","src":13,"more_decls":null}{"pl":"const TAG_member = 0x0d","src":14,"more_decls":null}{"pl":"const TAG_pointer_type = 0x0f","src":15,"more_decls":null}{"pl":"const TAG_reference_type = 0x10","src":16,"more_decls":null}{"pl":"const TAG_compile_unit = 0x11","src":17,"more_decls":null}{"pl":"const TAG_string_type = 0x12","src":18,"more_decls":null}{"pl":"const TAG_structure_type = 0x13","src":19,"more_decls":null}{"pl":"const TAG_subroutine = 0x14","src":20,"more_decls":null}{"pl":"const TAG_subroutine_type = 0x15","src":21,"more_decls":null}{"pl":"const TAG_typedef = 0x16","src":22,"more_decls":null}{"pl":"const TAG_union_type = 0x17","src":23,"more_decls":null}{"pl":"const TAG_unspecified_parameters = 0x18","src":24,"more_decls":null}{"pl":"const TAG_variant = 0x19","src":25,"more_decls":null}{"pl":"const TAG_common_block = 0x1a","src":26,"more_decls":null}{"pl":"const TAG_common_inclusion = 0x1b","src":27,"more_decls":null}{"pl":"const TAG_inheritance = 0x1c","src":28,"more_decls":null}{"pl":"const TAG_inlined_subroutine = 0x1d","src":29,"more_decls":null}{"pl":"const TAG_module = 0x1e","src":30,"more_decls":null}{"pl":"const TAG_ptr_to_member_type = 0x1f","src":31,"more_decls":null}{"pl":"const TAG_set_type = 0x20","src":32,"more_decls":null}{"pl":"const TAG_subrange_type = 0x21","src":33,"more_decls":null}{"pl":"const TAG_with_stmt = 0x22","src":34,"more_decls":null}{"pl":"const TAG_access_declaration = 0x23","src":35,"more_decls":null}{"pl":"const TAG_base_type = 0x24","src":36,"more_decls":null}{"pl":"const TAG_catch_block = 0x25","src":37,"more_decls":null}{"pl":"const TAG_const_type = 0x26","src":38,"more_decls":null}{"pl":"const TAG_constant = 0x27","src":39,"more_decls":null}{"pl":"const TAG_enumerator = 0x28","src":40,"more_decls":null}{"pl":"const TAG_file_type = 0x29","src":41,"more_decls":null}{"pl":"const TAG_friend = 0x2a","src":42,"more_decls":null}{"pl":"const TAG_namelist = 0x2b","src":43,"more_decls":null}{"pl":"const TAG_namelist_item = 0x2c","src":44,"more_decls":null}{"pl":"const TAG_packed_type = 0x2d","src":45,"more_decls":null}{"pl":"const TAG_subprogram = 0x2e","src":46,"more_decls":null}{"pl":"const TAG_template_type_param = 0x2f","src":47,"more_decls":null}{"pl":"const TAG_template_value_param = 0x30","src":48,"more_decls":null}{"pl":"const TAG_thrown_type = 0x31","src":49,"more_decls":null}{"pl":"const TAG_try_block = 0x32","src":50,"more_decls":null}{"pl":"const TAG_variant_part = 0x33","src":51,"more_decls":null}{"pl":"const TAG_variable = 0x34","src":52,"more_decls":null}{"pl":"const TAG_volatile_type = 0x35","src":53,"more_decls":null}{"pl":"const TAG_dwarf_procedure = 0x36","src":56,"more_decls":null}{"pl":"const TAG_restrict_type = 0x37","src":57,"more_decls":null}{"pl":"const TAG_interface_type = 0x38","src":58,"more_decls":null}{"pl":"const TAG_namespace = 0x39","src":59,"more_decls":null}{"pl":"const TAG_imported_module = 0x3a","src":60,"more_decls":null}{"pl":"const TAG_unspecified_type = 0x3b","src":61,"more_decls":null}{"pl":"const TAG_partial_unit = 0x3c","src":62,"more_decls":null}{"pl":"const TAG_imported_unit = 0x3d","src":63,"more_decls":null}{"pl":"const TAG_condition = 0x3f","src":64,"more_decls":null}{"pl":"const TAG_shared_type = 0x40","src":65,"more_decls":null}{"pl":"const TAG_type_unit = 0x41","src":68,"more_decls":null}{"pl":"const TAG_rvalue_reference_type = 0x42","src":69,"more_decls":null}{"pl":"const TAG_template_alias = 0x43","src":70,"more_decls":null}{"pl":"const TAG_lo_user = 0x4080","src":72,"more_decls":null}{"pl":"const TAG_hi_user = 0xffff","src":73,"more_decls":null}{"pl":"const TAG_MIPS_loop = 0x4081","src":76,"more_decls":null}{"pl":"const TAG_HP_array_descriptor = 0x4090","src":79,"more_decls":null}{"pl":"const TAG_HP_Bliss_field = 0x4091","src":80,"more_decls":null}{"pl":"const TAG_HP_Bliss_field_set = 0x4092","src":81,"more_decls":null}{"pl":"const TAG_format_label = 0x4101","src":84,"more_decls":null}{"pl":"const TAG_function_template = 0x4102","src":85,"more_decls":null}{"pl":"const TAG_class_template = 0x4103","src":86,"more_decls":null}{"pl":"const TAG_GNU_BINCL = 0x4104","src":87,"more_decls":null}{"pl":"const TAG_GNU_EINCL = 0x4105","src":88,"more_decls":null}{"pl":"const TAG_GNU_template_template_param = 0x4106","src":92,"more_decls":null}{"pl":"const TAG_GNU_template_parameter_pack = 0x4107","src":98,"more_decls":null}{"pl":"const TAG_GNU_formal_parameter_pack = 0x4108","src":99,"more_decls":null}{"pl":"const TAG_GNU_call_site = 0x4109","src":104,"more_decls":null}{"pl":"const TAG_GNU_call_site_parameter = 0x410a","src":105,"more_decls":null}{"pl":"const TAG_upc_shared_type = 0x8765","src":107,"more_decls":null}{"pl":"const TAG_upc_strict_type = 0x8766","src":108,"more_decls":null}{"pl":"const TAG_upc_relaxed_type = 0x8767","src":109,"more_decls":null}{"pl":"const TAG_PGI_kanji_type = 0xA000","src":111,"more_decls":null}{"pl":"const TAG_PGI_interface_block = 0xA020","src":112,"more_decls":null}{"pl":"const FORM_addr = 0x01","src":114,"more_decls":null}{"pl":"const FORM_block2 = 0x03","src":115,"more_decls":null}{"pl":"const FORM_block4 = 0x04","src":116,"more_decls":null}{"pl":"const FORM_data2 = 0x05","src":117,"more_decls":null}{"pl":"const FORM_data4 = 0x06","src":118,"more_decls":null}{"pl":"const FORM_data8 = 0x07","src":119,"more_decls":null}{"pl":"const FORM_string = 0x08","src":120,"more_decls":null}{"pl":"const FORM_block = 0x09","src":121,"more_decls":null}{"pl":"const FORM_block1 = 0x0a","src":122,"more_decls":null}{"pl":"const FORM_data1 = 0x0b","src":123,"more_decls":null}{"pl":"const FORM_flag = 0x0c","src":124,"more_decls":null}{"pl":"const FORM_sdata = 0x0d","src":125,"more_decls":null}{"pl":"const FORM_strp = 0x0e","src":126,"more_decls":null}{"pl":"const FORM_udata = 0x0f","src":127,"more_decls":null}{"pl":"const FORM_ref_addr = 0x10","src":128,"more_decls":null}{"pl":"const FORM_ref1 = 0x11","src":129,"more_decls":null}{"pl":"const FORM_ref2 = 0x12","src":130,"more_decls":null}{"pl":"const FORM_ref4 = 0x13","src":131,"more_decls":null}{"pl":"const FORM_ref8 = 0x14","src":132,"more_decls":null}{"pl":"const FORM_ref_udata = 0x15","src":133,"more_decls":null}{"pl":"const FORM_indirect = 0x16","src":134,"more_decls":null}{"pl":"const FORM_sec_offset = 0x17","src":135,"more_decls":null}{"pl":"const FORM_exprloc = 0x18","src":136,"more_decls":null}{"pl":"const FORM_flag_present = 0x19","src":137,"more_decls":null}{"pl":"const FORM_ref_sig8 = 0x20","src":138,"more_decls":null}{"pl":"const FORM_GNU_addr_index = 0x1f01","src":141,"more_decls":null}{"pl":"const FORM_GNU_str_index = 0x1f02","src":142,"more_decls":null}{"pl":"const FORM_GNU_ref_alt = 0x1f20","src":146,"more_decls":null}{"pl":"const FORM_GNU_strp_alt = 0x1f21","src":147,"more_decls":null}{"pl":"const AT_sibling = 0x01","src":149,"more_decls":null}{"pl":"const AT_location = 0x02","src":150,"more_decls":null}{"pl":"const AT_name = 0x03","src":151,"more_decls":null}{"pl":"const AT_ordering = 0x09","src":152,"more_decls":null}{"pl":"const AT_subscr_data = 0x0a","src":153,"more_decls":null}{"pl":"const AT_byte_size = 0x0b","src":154,"more_decls":null}{"pl":"const AT_bit_offset = 0x0c","src":155,"more_decls":null}{"pl":"const AT_bit_size = 0x0d","src":156,"more_decls":null}{"pl":"const AT_element_list = 0x0f","src":157,"more_decls":null}{"pl":"const AT_stmt_list = 0x10","src":158,"more_decls":null}{"pl":"const AT_low_pc = 0x11","src":159,"more_decls":null}{"pl":"const AT_high_pc = 0x12","src":160,"more_decls":null}{"pl":"const AT_language = 0x13","src":161,"more_decls":null}{"pl":"const AT_member = 0x14","src":162,"more_decls":null}{"pl":"const AT_discr = 0x15","src":163,"more_decls":null}{"pl":"const AT_discr_value = 0x16","src":164,"more_decls":null}{"pl":"const AT_visibility = 0x17","src":165,"more_decls":null}{"pl":"const AT_import = 0x18","src":166,"more_decls":null}{"pl":"const AT_string_length = 0x19","src":167,"more_decls":null}{"pl":"const AT_common_reference = 0x1a","src":168,"more_decls":null}{"pl":"const AT_comp_dir = 0x1b","src":169,"more_decls":null}{"pl":"const AT_const_value = 0x1c","src":170,"more_decls":null}{"pl":"const AT_containing_type = 0x1d","src":171,"more_decls":null}{"pl":"const AT_default_value = 0x1e","src":172,"more_decls":null}{"pl":"const AT_inline = 0x20","src":173,"more_decls":null}{"pl":"const AT_is_optional = 0x21","src":174,"more_decls":null}{"pl":"const AT_lower_bound = 0x22","src":175,"more_decls":null}{"pl":"const AT_producer = 0x25","src":176,"more_decls":null}{"pl":"const AT_prototyped = 0x27","src":177,"more_decls":null}{"pl":"const AT_return_addr = 0x2a","src":178,"more_decls":null}{"pl":"const AT_start_scope = 0x2c","src":179,"more_decls":null}{"pl":"const AT_bit_stride = 0x2e","src":180,"more_decls":null}{"pl":"const AT_upper_bound = 0x2f","src":181,"more_decls":null}{"pl":"const AT_abstract_origin = 0x31","src":182,"more_decls":null}{"pl":"const AT_accessibility = 0x32","src":183,"more_decls":null}{"pl":"const AT_address_class = 0x33","src":184,"more_decls":null}{"pl":"const AT_artificial = 0x34","src":185,"more_decls":null}{"pl":"const AT_base_types = 0x35","src":186,"more_decls":null}{"pl":"const AT_calling_convention = 0x36","src":187,"more_decls":null}{"pl":"const AT_count = 0x37","src":188,"more_decls":null}{"pl":"const AT_data_member_location = 0x38","src":189,"more_decls":null}{"pl":"const AT_decl_column = 0x39","src":190,"more_decls":null}{"pl":"const AT_decl_file = 0x3a","src":191,"more_decls":null}{"pl":"const AT_decl_line = 0x3b","src":192,"more_decls":null}{"pl":"const AT_declaration = 0x3c","src":193,"more_decls":null}{"pl":"const AT_discr_list = 0x3d","src":194,"more_decls":null}{"pl":"const AT_encoding = 0x3e","src":195,"more_decls":null}{"pl":"const AT_external = 0x3f","src":196,"more_decls":null}{"pl":"const AT_frame_base = 0x40","src":197,"more_decls":null}{"pl":"const AT_friend = 0x41","src":198,"more_decls":null}{"pl":"const AT_identifier_case = 0x42","src":199,"more_decls":null}{"pl":"const AT_macro_info = 0x43","src":200,"more_decls":null}{"pl":"const AT_namelist_items = 0x44","src":201,"more_decls":null}{"pl":"const AT_priority = 0x45","src":202,"more_decls":null}{"pl":"const AT_segment = 0x46","src":203,"more_decls":null}{"pl":"const AT_specification = 0x47","src":204,"more_decls":null}{"pl":"const AT_static_link = 0x48","src":205,"more_decls":null}{"pl":"const AT_type = 0x49","src":206,"more_decls":null}{"pl":"const AT_use_location = 0x4a","src":207,"more_decls":null}{"pl":"const AT_variable_parameter = 0x4b","src":208,"more_decls":null}{"pl":"const AT_virtuality = 0x4c","src":209,"more_decls":null}{"pl":"const AT_vtable_elem_location = 0x4d","src":210,"more_decls":null}{"pl":"const AT_allocated = 0x4e","src":213,"more_decls":null}{"pl":"const AT_associated = 0x4f","src":214,"more_decls":null}{"pl":"const AT_data_location = 0x50","src":215,"more_decls":null}{"pl":"const AT_byte_stride = 0x51","src":216,"more_decls":null}{"pl":"const AT_entry_pc = 0x52","src":217,"more_decls":null}{"pl":"const AT_use_UTF8 = 0x53","src":218,"more_decls":null}{"pl":"const AT_extension = 0x54","src":219,"more_decls":null}{"pl":"const AT_ranges = 0x55","src":220,"more_decls":null}{"pl":"const AT_trampoline = 0x56","src":221,"more_decls":null}{"pl":"const AT_call_column = 0x57","src":222,"more_decls":null}{"pl":"const AT_call_file = 0x58","src":223,"more_decls":null}{"pl":"const AT_call_line = 0x59","src":224,"more_decls":null}{"pl":"const AT_description = 0x5a","src":225,"more_decls":null}{"pl":"const AT_binary_scale = 0x5b","src":226,"more_decls":null}{"pl":"const AT_decimal_scale = 0x5c","src":227,"more_decls":null}{"pl":"const AT_small = 0x5d","src":228,"more_decls":null}{"pl":"const AT_decimal_sign = 0x5e","src":229,"more_decls":null}{"pl":"const AT_digit_count = 0x5f","src":230,"more_decls":null}{"pl":"const AT_picture_string = 0x60","src":231,"more_decls":null}{"pl":"const AT_mutable = 0x61","src":232,"more_decls":null}{"pl":"const AT_threads_scaled = 0x62","src":233,"more_decls":null}{"pl":"const AT_explicit = 0x63","src":234,"more_decls":null}{"pl":"const AT_object_pointer = 0x64","src":235,"more_decls":null}{"pl":"const AT_endianity = 0x65","src":236,"more_decls":null}{"pl":"const AT_elemental = 0x66","src":237,"more_decls":null}{"pl":"const AT_pure = 0x67","src":238,"more_decls":null}{"pl":"const AT_recursive = 0x68","src":239,"more_decls":null}{"pl":"const AT_signature = 0x69","src":242,"more_decls":null}{"pl":"const AT_main_subprogram = 0x6a","src":243,"more_decls":null}{"pl":"const AT_data_bit_offset = 0x6b","src":244,"more_decls":null}{"pl":"const AT_const_expr = 0x6c","src":245,"more_decls":null}{"pl":"const AT_enum_class = 0x6d","src":246,"more_decls":null}{"pl":"const AT_linkage_name = 0x6e","src":247,"more_decls":null}{"pl":"const AT_alignment = 0x88","src":250,"more_decls":null}{"pl":"const AT_lo_user = 0x2000","src":252,"more_decls":null}{"pl":"const AT_hi_user = 0x3fff","src":253,"more_decls":null}{"pl":"const AT_MIPS_fde = 0x2001","src":256,"more_decls":null}{"pl":"const AT_MIPS_loop_begin = 0x2002","src":257,"more_decls":null}{"pl":"const AT_MIPS_tail_loop_begin = 0x2003","src":258,"more_decls":null}{"pl":"const AT_MIPS_epilog_begin = 0x2004","src":259,"more_decls":null}{"pl":"const AT_MIPS_loop_unroll_factor = 0x2005","src":260,"more_decls":null}{"pl":"const AT_MIPS_software_pipeline_depth = 0x2006","src":261,"more_decls":null}{"pl":"const AT_MIPS_linkage_name = 0x2007","src":262,"more_decls":null}{"pl":"const AT_MIPS_stride = 0x2008","src":263,"more_decls":null}{"pl":"const AT_MIPS_abstract_name = 0x2009","src":264,"more_decls":null}{"pl":"const AT_MIPS_clone_origin = 0x200a","src":265,"more_decls":null}{"pl":"const AT_MIPS_has_inlines = 0x200b","src":266,"more_decls":null}{"pl":"const AT_HP_block_index = 0x2000","src":269,"more_decls":null}{"pl":"const AT_HP_unmodifiable = 0x2001","src":270,"more_decls":null}{"pl":"const AT_HP_prologue = 0x2005","src":271,"more_decls":null}{"pl":"const AT_HP_epilogue = 0x2008","src":272,"more_decls":null}{"pl":"const AT_HP_actuals_stmt_list = 0x2010","src":273,"more_decls":null}{"pl":"const AT_HP_proc_per_section = 0x2011","src":274,"more_decls":null}{"pl":"const AT_HP_raw_data_ptr = 0x2012","src":275,"more_decls":null}{"pl":"const AT_HP_pass_by_reference = 0x2013","src":276,"more_decls":null}{"pl":"const AT_HP_opt_level = 0x2014","src":277,"more_decls":null}{"pl":"const AT_HP_prof_version_id = 0x2015","src":278,"more_decls":null}{"pl":"const AT_HP_opt_flags = 0x2016","src":279,"more_decls":null}{"pl":"const AT_HP_cold_region_low_pc = 0x2017","src":280,"more_decls":null}{"pl":"const AT_HP_cold_region_high_pc = 0x2018","src":281,"more_decls":null}{"pl":"const AT_HP_all_variables_modifiable = 0x2019","src":282,"more_decls":null}{"pl":"const AT_HP_linkage_name = 0x201a","src":283,"more_decls":null}{"pl":"const AT_HP_prof_flags = 0x201b","src":284,"more_decls":null}{"pl":"const AT_HP_unit_name = 0x201f","src":285,"more_decls":null}{"pl":"const AT_HP_unit_size = 0x2020","src":286,"more_decls":null}{"pl":"const AT_HP_widened_byte_size = 0x2021","src":287,"more_decls":null}{"pl":"const AT_HP_definition_points = 0x2022","src":288,"more_decls":null}{"pl":"const AT_HP_default_location = 0x2023","src":289,"more_decls":null}{"pl":"const AT_HP_is_result_param = 0x2029","src":290,"more_decls":null}{"pl":"const AT_sf_names = 0x2101","src":293,"more_decls":null}{"pl":"const AT_src_info = 0x2102","src":294,"more_decls":null}{"pl":"const AT_mac_info = 0x2103","src":295,"more_decls":null}{"pl":"const AT_src_coords = 0x2104","src":296,"more_decls":null}{"pl":"const AT_body_begin = 0x2105","src":297,"more_decls":null}{"pl":"const AT_body_end = 0x2106","src":298,"more_decls":null}{"pl":"const AT_GNU_vector = 0x2107","src":299,"more_decls":null}{"pl":"const AT_GNU_guarded_by = 0x2108","src":302,"more_decls":null}{"pl":"const AT_GNU_pt_guarded_by = 0x2109","src":303,"more_decls":null}{"pl":"const AT_GNU_guarded = 0x210a","src":304,"more_decls":null}{"pl":"const AT_GNU_pt_guarded = 0x210b","src":305,"more_decls":null}{"pl":"const AT_GNU_locks_excluded = 0x210c","src":306,"more_decls":null}{"pl":"const AT_GNU_exclusive_locks_required = 0x210d","src":307,"more_decls":null}{"pl":"const AT_GNU_shared_locks_required = 0x210e","src":308,"more_decls":null}{"pl":"const AT_GNU_odr_signature = 0x210f","src":311,"more_decls":null}{"pl":"const AT_GNU_template_name = 0x2110","src":314,"more_decls":null}{"pl":"const AT_GNU_call_site_value = 0x2111","src":317,"more_decls":null}{"pl":"const AT_GNU_call_site_data_value = 0x2112","src":318,"more_decls":null}{"pl":"const AT_GNU_call_site_target = 0x2113","src":319,"more_decls":null}{"pl":"const AT_GNU_call_site_target_clobbered = 0x2114","src":320,"more_decls":null}{"pl":"const AT_GNU_tail_call = 0x2115","src":321,"more_decls":null}{"pl":"const AT_GNU_all_tail_call_sites = 0x2116","src":322,"more_decls":null}{"pl":"const AT_GNU_all_call_sites = 0x2117","src":323,"more_decls":null}{"pl":"const AT_GNU_all_source_call_sites = 0x2118","src":324,"more_decls":null}{"pl":"const AT_GNU_macros = 0x2119","src":326,"more_decls":null}{"pl":"const AT_GNU_dwo_name = 0x2130","src":328,"more_decls":null}{"pl":"const AT_GNU_dwo_id = 0x2131","src":329,"more_decls":null}{"pl":"const AT_GNU_ranges_base = 0x2132","src":330,"more_decls":null}{"pl":"const AT_GNU_addr_base = 0x2133","src":331,"more_decls":null}{"pl":"const AT_GNU_pubnames = 0x2134","src":332,"more_decls":null}{"pl":"const AT_GNU_pubtypes = 0x2135","src":333,"more_decls":null}{"pl":"const AT_VMS_rtnbeg_pd_address = 0x2201","src":335,"more_decls":null}{"pl":"const AT_use_GNAT_descriptive_type = 0x2301","src":339,"more_decls":null}{"pl":"const AT_GNAT_descriptive_type = 0x2302","src":340,"more_decls":null}{"pl":"const AT_upc_threads_scaled = 0x3210","src":342,"more_decls":null}{"pl":"const AT_PGI_lbase = 0x3a00","src":344,"more_decls":null}{"pl":"const AT_PGI_soffset = 0x3a01","src":345,"more_decls":null}{"pl":"const AT_PGI_lstride = 0x3a02","src":346,"more_decls":null}{"pl":"const OP_addr = 0x03","src":348,"more_decls":null}{"pl":"const OP_deref = 0x06","src":349,"more_decls":null}{"pl":"const OP_const1u = 0x08","src":350,"more_decls":null}{"pl":"const OP_const1s = 0x09","src":351,"more_decls":null}{"pl":"const OP_const2u = 0x0a","src":352,"more_decls":null}{"pl":"const OP_const2s = 0x0b","src":353,"more_decls":null}{"pl":"const OP_const4u = 0x0c","src":354,"more_decls":null}{"pl":"const OP_const4s = 0x0d","src":355,"more_decls":null}{"pl":"const OP_const8u = 0x0e","src":356,"more_decls":null}{"pl":"const OP_const8s = 0x0f","src":357,"more_decls":null}{"pl":"const OP_constu = 0x10","src":358,"more_decls":null}{"pl":"const OP_consts = 0x11","src":359,"more_decls":null}{"pl":"const OP_dup = 0x12","src":360,"more_decls":null}{"pl":"const OP_drop = 0x13","src":361,"more_decls":null}{"pl":"const OP_over = 0x14","src":362,"more_decls":null}{"pl":"const OP_pick = 0x15","src":363,"more_decls":null}{"pl":"const OP_swap = 0x16","src":364,"more_decls":null}{"pl":"const OP_rot = 0x17","src":365,"more_decls":null}{"pl":"const OP_xderef = 0x18","src":366,"more_decls":null}{"pl":"const OP_abs = 0x19","src":367,"more_decls":null}{"pl":"const OP_and = 0x1a","src":368,"more_decls":null}{"pl":"const OP_div = 0x1b","src":369,"more_decls":null}{"pl":"const OP_minus = 0x1c","src":370,"more_decls":null}{"pl":"const OP_mod = 0x1d","src":371,"more_decls":null}{"pl":"const OP_mul = 0x1e","src":372,"more_decls":null}{"pl":"const OP_neg = 0x1f","src":373,"more_decls":null}{"pl":"const OP_not = 0x20","src":374,"more_decls":null}{"pl":"const OP_or = 0x21","src":375,"more_decls":null}{"pl":"const OP_plus = 0x22","src":376,"more_decls":null}{"pl":"const OP_plus_uconst = 0x23","src":377,"more_decls":null}{"pl":"const OP_shl = 0x24","src":378,"more_decls":null}{"pl":"const OP_shr = 0x25","src":379,"more_decls":null}{"pl":"const OP_shra = 0x26","src":380,"more_decls":null}{"pl":"const OP_xor = 0x27","src":381,"more_decls":null}{"pl":"const OP_bra = 0x28","src":382,"more_decls":null}{"pl":"const OP_eq = 0x29","src":383,"more_decls":null}{"pl":"const OP_ge = 0x2a","src":384,"more_decls":null}{"pl":"const OP_gt = 0x2b","src":385,"more_decls":null}{"pl":"const OP_le = 0x2c","src":386,"more_decls":null}{"pl":"const OP_lt = 0x2d","src":387,"more_decls":null}{"pl":"const OP_ne = 0x2e","src":388,"more_decls":null}{"pl":"const OP_skip = 0x2f","src":389,"more_decls":null}{"pl":"const OP_lit0 = 0x30","src":390,"more_decls":null}{"pl":"const OP_lit1 = 0x31","src":391,"more_decls":null}{"pl":"const OP_lit2 = 0x32","src":392,"more_decls":null}{"pl":"const OP_lit3 = 0x33","src":393,"more_decls":null}{"pl":"const OP_lit4 = 0x34","src":394,"more_decls":null}{"pl":"const OP_lit5 = 0x35","src":395,"more_decls":null}{"pl":"const OP_lit6 = 0x36","src":396,"more_decls":null}{"pl":"const OP_lit7 = 0x37","src":397,"more_decls":null}{"pl":"const OP_lit8 = 0x38","src":398,"more_decls":null}{"pl":"const OP_lit9 = 0x39","src":399,"more_decls":null}{"pl":"const OP_lit10 = 0x3a","src":400,"more_decls":null}{"pl":"const OP_lit11 = 0x3b","src":401,"more_decls":null}{"pl":"const OP_lit12 = 0x3c","src":402,"more_decls":null}{"pl":"const OP_lit13 = 0x3d","src":403,"more_decls":null}{"pl":"const OP_lit14 = 0x3e","src":404,"more_decls":null}{"pl":"const OP_lit15 = 0x3f","src":405,"more_decls":null}{"pl":"const OP_lit16 = 0x40","src":406,"more_decls":null}{"pl":"const OP_lit17 = 0x41","src":407,"more_decls":null}{"pl":"const OP_lit18 = 0x42","src":408,"more_decls":null}{"pl":"const OP_lit19 = 0x43","src":409,"more_decls":null}{"pl":"const OP_lit20 = 0x44","src":410,"more_decls":null}{"pl":"const OP_lit21 = 0x45","src":411,"more_decls":null}{"pl":"const OP_lit22 = 0x46","src":412,"more_decls":null}{"pl":"const OP_lit23 = 0x47","src":413,"more_decls":null}{"pl":"const OP_lit24 = 0x48","src":414,"more_decls":null}{"pl":"const OP_lit25 = 0x49","src":415,"more_decls":null}{"pl":"const OP_lit26 = 0x4a","src":416,"more_decls":null}{"pl":"const OP_lit27 = 0x4b","src":417,"more_decls":null}{"pl":"const OP_lit28 = 0x4c","src":418,"more_decls":null}{"pl":"const OP_lit29 = 0x4d","src":419,"more_decls":null}{"pl":"const OP_lit30 = 0x4e","src":420,"more_decls":null}{"pl":"const OP_lit31 = 0x4f","src":421,"more_decls":null}{"pl":"const OP_reg0 = 0x50","src":422,"more_decls":null}{"pl":"const OP_reg1 = 0x51","src":423,"more_decls":null}{"pl":"const OP_reg2 = 0x52","src":424,"more_decls":null}{"pl":"const OP_reg3 = 0x53","src":425,"more_decls":null}{"pl":"const OP_reg4 = 0x54","src":426,"more_decls":null}{"pl":"const OP_reg5 = 0x55","src":427,"more_decls":null}{"pl":"const OP_reg6 = 0x56","src":428,"more_decls":null}{"pl":"const OP_reg7 = 0x57","src":429,"more_decls":null}{"pl":"const OP_reg8 = 0x58","src":430,"more_decls":null}{"pl":"const OP_reg9 = 0x59","src":431,"more_decls":null}{"pl":"const OP_reg10 = 0x5a","src":432,"more_decls":null}{"pl":"const OP_reg11 = 0x5b","src":433,"more_decls":null}{"pl":"const OP_reg12 = 0x5c","src":434,"more_decls":null}{"pl":"const OP_reg13 = 0x5d","src":435,"more_decls":null}{"pl":"const OP_reg14 = 0x5e","src":436,"more_decls":null}{"pl":"const OP_reg15 = 0x5f","src":437,"more_decls":null}{"pl":"const OP_reg16 = 0x60","src":438,"more_decls":null}{"pl":"const OP_reg17 = 0x61","src":439,"more_decls":null}{"pl":"const OP_reg18 = 0x62","src":440,"more_decls":null}{"pl":"const OP_reg19 = 0x63","src":441,"more_decls":null}{"pl":"const OP_reg20 = 0x64","src":442,"more_decls":null}{"pl":"const OP_reg21 = 0x65","src":443,"more_decls":null}{"pl":"const OP_reg22 = 0x66","src":444,"more_decls":null}{"pl":"const OP_reg23 = 0x67","src":445,"more_decls":null}{"pl":"const OP_reg24 = 0x68","src":446,"more_decls":null}{"pl":"const OP_reg25 = 0x69","src":447,"more_decls":null}{"pl":"const OP_reg26 = 0x6a","src":448,"more_decls":null}{"pl":"const OP_reg27 = 0x6b","src":449,"more_decls":null}{"pl":"const OP_reg28 = 0x6c","src":450,"more_decls":null}{"pl":"const OP_reg29 = 0x6d","src":451,"more_decls":null}{"pl":"const OP_reg30 = 0x6e","src":452,"more_decls":null}{"pl":"const OP_reg31 = 0x6f","src":453,"more_decls":null}{"pl":"const OP_breg0 = 0x70","src":454,"more_decls":null}{"pl":"const OP_breg1 = 0x71","src":455,"more_decls":null}{"pl":"const OP_breg2 = 0x72","src":456,"more_decls":null}{"pl":"const OP_breg3 = 0x73","src":457,"more_decls":null}{"pl":"const OP_breg4 = 0x74","src":458,"more_decls":null}{"pl":"const OP_breg5 = 0x75","src":459,"more_decls":null}{"pl":"const OP_breg6 = 0x76","src":460,"more_decls":null}{"pl":"const OP_breg7 = 0x77","src":461,"more_decls":null}{"pl":"const OP_breg8 = 0x78","src":462,"more_decls":null}{"pl":"const OP_breg9 = 0x79","src":463,"more_decls":null}{"pl":"const OP_breg10 = 0x7a","src":464,"more_decls":null}{"pl":"const OP_breg11 = 0x7b","src":465,"more_decls":null}{"pl":"const OP_breg12 = 0x7c","src":466,"more_decls":null}{"pl":"const OP_breg13 = 0x7d","src":467,"more_decls":null}{"pl":"const OP_breg14 = 0x7e","src":468,"more_decls":null}{"pl":"const OP_breg15 = 0x7f","src":469,"more_decls":null}{"pl":"const OP_breg16 = 0x80","src":470,"more_decls":null}{"pl":"const OP_breg17 = 0x81","src":471,"more_decls":null}{"pl":"const OP_breg18 = 0x82","src":472,"more_decls":null}{"pl":"const OP_breg19 = 0x83","src":473,"more_decls":null}{"pl":"const OP_breg20 = 0x84","src":474,"more_decls":null}{"pl":"const OP_breg21 = 0x85","src":475,"more_decls":null}{"pl":"const OP_breg22 = 0x86","src":476,"more_decls":null}{"pl":"const OP_breg23 = 0x87","src":477,"more_decls":null}{"pl":"const OP_breg24 = 0x88","src":478,"more_decls":null}{"pl":"const OP_breg25 = 0x89","src":479,"more_decls":null}{"pl":"const OP_breg26 = 0x8a","src":480,"more_decls":null}{"pl":"const OP_breg27 = 0x8b","src":481,"more_decls":null}{"pl":"const OP_breg28 = 0x8c","src":482,"more_decls":null}{"pl":"const OP_breg29 = 0x8d","src":483,"more_decls":null}{"pl":"const OP_breg30 = 0x8e","src":484,"more_decls":null}{"pl":"const OP_breg31 = 0x8f","src":485,"more_decls":null}{"pl":"const OP_regx = 0x90","src":486,"more_decls":null}{"pl":"const OP_fbreg = 0x91","src":487,"more_decls":null}{"pl":"const OP_bregx = 0x92","src":488,"more_decls":null}{"pl":"const OP_piece = 0x93","src":489,"more_decls":null}{"pl":"const OP_deref_size = 0x94","src":490,"more_decls":null}{"pl":"const OP_xderef_size = 0x95","src":491,"more_decls":null}{"pl":"const OP_nop = 0x96","src":492,"more_decls":null}{"pl":"const OP_push_object_address = 0x97","src":495,"more_decls":null}{"pl":"const OP_call2 = 0x98","src":496,"more_decls":null}{"pl":"const OP_call4 = 0x99","src":497,"more_decls":null}{"pl":"const OP_call_ref = 0x9a","src":498,"more_decls":null}{"pl":"const OP_form_tls_address = 0x9b","src":499,"more_decls":null}{"pl":"const OP_call_frame_cfa = 0x9c","src":500,"more_decls":null}{"pl":"const OP_bit_piece = 0x9d","src":501,"more_decls":null}{"pl":"const OP_implicit_value = 0x9e","src":504,"more_decls":null}{"pl":"const OP_stack_value = 0x9f","src":505,"more_decls":null}{"pl":"const OP_lo_user = 0xe0","src":507,"more_decls":null}{"pl":"const OP_hi_user = 0xff","src":508,"more_decls":null}{"pl":"const OP_GNU_push_tls_address = 0xe0","src":511,"more_decls":null}{"pl":"const OP_GNU_uninit = 0xf0","src":513,"more_decls":null}{"pl":"const OP_GNU_encoded_addr = 0xf1","src":514,"more_decls":null}{"pl":"const OP_GNU_implicit_pointer = 0xf2","src":517,"more_decls":null}{"pl":"const OP_GNU_entry_value = 0xf3","src":520,"more_decls":null}{"pl":"const OP_GNU_const_type = 0xf4","src":523,"more_decls":null}{"pl":"const OP_GNU_regval_type = 0xf5","src":524,"more_decls":null}{"pl":"const OP_GNU_deref_type = 0xf6","src":525,"more_decls":null}{"pl":"const OP_GNU_convert = 0xf7","src":526,"more_decls":null}{"pl":"const OP_GNU_reinterpret = 0xf9","src":527,"more_decls":null}{"pl":"const OP_GNU_parameter_ref = 0xfa","src":529,"more_decls":null}{"pl":"const OP_GNU_addr_index = 0xfb","src":531,"more_decls":null}{"pl":"const OP_GNU_const_index = 0xfc","src":532,"more_decls":null}{"pl":"const OP_HP_unknown = 0xe0","src":534,"more_decls":null}{"pl":"const OP_HP_is_value = 0xe1","src":535,"more_decls":null}{"pl":"const OP_HP_fltconst4 = 0xe2","src":536,"more_decls":null}{"pl":"const OP_HP_fltconst8 = 0xe3","src":537,"more_decls":null}{"pl":"const OP_HP_mod_range = 0xe4","src":538,"more_decls":null}{"pl":"const OP_HP_unmod_range = 0xe5","src":539,"more_decls":null}{"pl":"const OP_HP_tls = 0xe6","src":540,"more_decls":null}{"pl":"const OP_PGI_omp_thread_num = 0xf8","src":542,"more_decls":null}{"pl":"const ATE_void = 0x0","src":544,"more_decls":null}{"pl":"const ATE_address = 0x1","src":545,"more_decls":null}{"pl":"const ATE_boolean = 0x2","src":546,"more_decls":null}{"pl":"const ATE_complex_float = 0x3","src":547,"more_decls":null}{"pl":"const ATE_float = 0x4","src":548,"more_decls":null}{"pl":"const ATE_signed = 0x5","src":549,"more_decls":null}{"pl":"const ATE_signed_char = 0x6","src":550,"more_decls":null}{"pl":"const ATE_unsigned = 0x7","src":551,"more_decls":null}{"pl":"const ATE_unsigned_char = 0x8","src":552,"more_decls":null}{"pl":"const ATE_imaginary_float = 0x9","src":555,"more_decls":null}{"pl":"const ATE_packed_decimal = 0xa","src":556,"more_decls":null}{"pl":"const ATE_numeric_string = 0xb","src":557,"more_decls":null}{"pl":"const ATE_edited = 0xc","src":558,"more_decls":null}{"pl":"const ATE_signed_fixed = 0xd","src":559,"more_decls":null}{"pl":"const ATE_unsigned_fixed = 0xe","src":560,"more_decls":null}{"pl":"const ATE_decimal_float = 0xf","src":561,"more_decls":null}{"pl":"const ATE_UTF = 0x10","src":564,"more_decls":null}{"pl":"const ATE_lo_user = 0x80","src":566,"more_decls":null}{"pl":"const ATE_hi_user = 0xff","src":567,"more_decls":null}{"pl":"const ATE_HP_float80 = 0x80","src":570,"more_decls":null}{"pl":"const ATE_HP_complex_float80 = 0x81","src":571,"more_decls":null}{"pl":"const ATE_HP_float128 = 0x82","src":572,"more_decls":null}{"pl":"const ATE_HP_complex_float128 = 0x83","src":573,"more_decls":null}{"pl":"const ATE_HP_floathpintel = 0x84","src":574,"more_decls":null}{"pl":"const ATE_HP_imaginary_float80 = 0x85","src":575,"more_decls":null}{"pl":"const ATE_HP_imaginary_float128 = 0x86","src":576,"more_decls":null}{"pl":"const ATE_HP_VAX_float = 0x88","src":577,"more_decls":null}{"pl":"const ATE_HP_VAX_float_d = 0x89","src":578,"more_decls":null}{"pl":"const ATE_HP_packed_decimal = 0x8a","src":579,"more_decls":null}{"pl":"const ATE_HP_zoned_decimal = 0x8b","src":580,"more_decls":null}{"pl":"const ATE_HP_edited = 0x8c","src":581,"more_decls":null}{"pl":"const ATE_HP_signed_fixed = 0x8d","src":582,"more_decls":null}{"pl":"const ATE_HP_unsigned_fixed = 0x8e","src":583,"more_decls":null}{"pl":"const ATE_HP_VAX_complex_float = 0x8f","src":584,"more_decls":null}{"pl":"const ATE_HP_VAX_complex_float_d = 0x90","src":585,"more_decls":null}{"pl":"const CFA_advance_loc = 0x40","src":587,"more_decls":null}{"pl":"const CFA_offset = 0x80","src":588,"more_decls":null}{"pl":"const CFA_restore = 0xc0","src":589,"more_decls":null}{"pl":"const CFA_nop = 0x00","src":590,"more_decls":null}{"pl":"const CFA_set_loc = 0x01","src":591,"more_decls":null}{"pl":"const CFA_advance_loc1 = 0x02","src":592,"more_decls":null}{"pl":"const CFA_advance_loc2 = 0x03","src":593,"more_decls":null}{"pl":"const CFA_advance_loc4 = 0x04","src":594,"more_decls":null}{"pl":"const CFA_offset_extended = 0x05","src":595,"more_decls":null}{"pl":"const CFA_restore_extended = 0x06","src":596,"more_decls":null}{"pl":"const CFA_undefined = 0x07","src":597,"more_decls":null}{"pl":"const CFA_same_value = 0x08","src":598,"more_decls":null}{"pl":"const CFA_register = 0x09","src":599,"more_decls":null}{"pl":"const CFA_remember_state = 0x0a","src":600,"more_decls":null}{"pl":"const CFA_restore_state = 0x0b","src":601,"more_decls":null}{"pl":"const CFA_def_cfa = 0x0c","src":602,"more_decls":null}{"pl":"const CFA_def_cfa_register = 0x0d","src":603,"more_decls":null}{"pl":"const CFA_def_cfa_offset = 0x0e","src":604,"more_decls":null}{"pl":"const CFA_def_cfa_expression = 0x0f","src":607,"more_decls":null}{"pl":"const CFA_expression = 0x10","src":608,"more_decls":null}{"pl":"const CFA_offset_extended_sf = 0x11","src":609,"more_decls":null}{"pl":"const CFA_def_cfa_sf = 0x12","src":610,"more_decls":null}{"pl":"const CFA_def_cfa_offset_sf = 0x13","src":611,"more_decls":null}{"pl":"const CFA_val_offset = 0x14","src":612,"more_decls":null}{"pl":"const CFA_val_offset_sf = 0x15","src":613,"more_decls":null}{"pl":"const CFA_val_expression = 0x16","src":614,"more_decls":null}{"pl":"const CFA_lo_user = 0x1c","src":616,"more_decls":null}{"pl":"const CFA_hi_user = 0x3f","src":617,"more_decls":null}{"pl":"const CFA_MIPS_advance_loc8 = 0x1d","src":620,"more_decls":null}{"pl":"const CFA_GNU_window_save = 0x2d","src":623,"more_decls":null}{"pl":"const CFA_GNU_args_size = 0x2e","src":624,"more_decls":null}{"pl":"const CFA_GNU_negative_offset_extended = 0x2f","src":625,"more_decls":null}{"pl":"const CHILDREN_no = 0x00","src":627,"more_decls":null}{"pl":"const CHILDREN_yes = 0x01","src":628,"more_decls":null}{"pl":"const LNS_extended_op = 0x00","src":630,"more_decls":null}{"pl":"const LNS_copy = 0x01","src":631,"more_decls":null}{"pl":"const LNS_advance_pc = 0x02","src":632,"more_decls":null}{"pl":"const LNS_advance_line = 0x03","src":633,"more_decls":null}{"pl":"const LNS_set_file = 0x04","src":634,"more_decls":null}{"pl":"const LNS_set_column = 0x05","src":635,"more_decls":null}{"pl":"const LNS_negate_stmt = 0x06","src":636,"more_decls":null}{"pl":"const LNS_set_basic_block = 0x07","src":637,"more_decls":null}{"pl":"const LNS_const_add_pc = 0x08","src":638,"more_decls":null}{"pl":"const LNS_fixed_advance_pc = 0x09","src":639,"more_decls":null}{"pl":"const LNS_set_prologue_end = 0x0a","src":640,"more_decls":null}{"pl":"const LNS_set_epilogue_begin = 0x0b","src":641,"more_decls":null}{"pl":"const LNS_set_isa = 0x0c","src":642,"more_decls":null}{"pl":"const LNE_end_sequence = 0x01","src":644,"more_decls":null}{"pl":"const LNE_set_address = 0x02","src":645,"more_decls":null}{"pl":"const LNE_define_file = 0x03","src":646,"more_decls":null}{"pl":"const LNE_set_discriminator = 0x04","src":647,"more_decls":null}{"pl":"const LNE_lo_user = 0x80","src":648,"more_decls":null}{"pl":"const LNE_hi_user = 0xff","src":649,"more_decls":null}{"pl":"const LANG_C89 = 0x0001","src":651,"more_decls":null}{"pl":"const LANG_C = 0x0002","src":652,"more_decls":null}{"pl":"const LANG_Ada83 = 0x0003","src":653,"more_decls":null}{"pl":"const LANG_C_plus_plus = 0x0004","src":654,"more_decls":null}{"pl":"const LANG_Cobol74 = 0x0005","src":655,"more_decls":null}{"pl":"const LANG_Cobol85 = 0x0006","src":656,"more_decls":null}{"pl":"const LANG_Fortran77 = 0x0007","src":657,"more_decls":null}{"pl":"const LANG_Fortran90 = 0x0008","src":658,"more_decls":null}{"pl":"const LANG_Pascal83 = 0x0009","src":659,"more_decls":null}{"pl":"const LANG_Modula2 = 0x000a","src":660,"more_decls":null}{"pl":"const LANG_Java = 0x000b","src":661,"more_decls":null}{"pl":"const LANG_C99 = 0x000c","src":662,"more_decls":null}{"pl":"const LANG_Ada95 = 0x000d","src":663,"more_decls":null}{"pl":"const LANG_Fortran95 = 0x000e","src":664,"more_decls":null}{"pl":"const LANG_PLI = 0x000f","src":665,"more_decls":null}{"pl":"const LANG_ObjC = 0x0010","src":666,"more_decls":null}{"pl":"const LANG_ObjC_plus_plus = 0x0011","src":667,"more_decls":null}{"pl":"const LANG_UPC = 0x0012","src":668,"more_decls":null}{"pl":"const LANG_D = 0x0013","src":669,"more_decls":null}{"pl":"const LANG_Python = 0x0014","src":670,"more_decls":null}{"pl":"const LANG_Go = 0x0016","src":671,"more_decls":null}{"pl":"const LANG_C_plus_plus_11 = 0x001a","src":672,"more_decls":null}{"pl":"const LANG_Rust = 0x001c","src":673,"more_decls":null}{"pl":"const LANG_C11 = 0x001d","src":674,"more_decls":null}{"pl":"const LANG_C_plus_plus_14 = 0x0021","src":675,"more_decls":null}{"pl":"const LANG_Fortran03 = 0x0022","src":676,"more_decls":null}{"pl":"const LANG_Fortran08 = 0x0023","src":677,"more_decls":null}{"pl":"const LANG_lo_user = 0x8000","src":678,"more_decls":null}{"pl":"const LANG_hi_user = 0xffff","src":679,"more_decls":null}{"pl":"const LANG_Mips_Assembler = 0x8001","src":680,"more_decls":null}{"pl":"const LANG_Upc = 0x8765","src":681,"more_decls":null}{"pl":"const LANG_HP_Bliss = 0x8003","src":682,"more_decls":null}{"pl":"const LANG_HP_Basic91 = 0x8004","src":683,"more_decls":null}{"pl":"const LANG_HP_Pascal91 = 0x8005","src":684,"more_decls":null}{"pl":"const LANG_HP_IMacro = 0x8006","src":685,"more_decls":null}{"pl":"const LANG_HP_Assembler = 0x8007","src":686,"more_decls":null}{"pl":"const UT_compile = 0x01","src":688,"more_decls":null}{"pl":"const UT_type = 0x02","src":689,"more_decls":null}{"pl":"const UT_partial = 0x03","src":690,"more_decls":null}{"pl":"const UT_skeleton = 0x04","src":691,"more_decls":null}{"pl":"const UT_split_compile = 0x05","src":692,"more_decls":null}{"pl":"const UT_split_type = 0x06","src":693,"more_decls":null}{"pl":"const UT_lo_user = 0x80","src":694,"more_decls":null}{"pl":"const UT_hi_user = 0xff","src":695,"more_decls":null}{"pl":"const LNCT_path = 0x1","src":697,"more_decls":null}{"pl":"const LNCT_directory_index = 0x2","src":698,"more_decls":null}{"pl":"const LNCT_timestamp = 0x3","src":699,"more_decls":null}{"pl":"const LNCT_size = 0x4","src":700,"more_decls":null}{"pl":"const LNCT_MD5 = 0x5","src":701,"more_decls":null}{"pl":"const LNCT_lo_user = 0x2000","src":702,"more_decls":null}{"pl":"const LNCT_hi_user = 0x3fff","src":703,"more_decls":null}]